gvalidate/__init__.py
gvalidate/callable.py
gvalidate/generic.py
gvalidate/numerical.py
gvalidate/string.py
gvalidate-0.0.1.dist-info/LICENSE
gvalidate-0.0.1.dist-info/METADATA
gvalidate-0.0.1.dist-info/WHEEL
gvalidate-0.0.1.dist-info/top_level.txt
gvalidate-0.0.1.dist-info/RECORD
