Metadata-Version: 2.1
Name: gvalidate
Version: 0.0.1
Summary: Generic validation decorators.
Home-page: https://github.com/simphotonics/gvalidate
Author: D Reschner
Author-email: git@simphotonics.com
License: UNKNOWN
Project-URL: Bug Tracker, https://github.com/simphotonics/gvalidate/issues
Platform: UNKNOWN
Classifier: Programming Language :: Python :: 3
Classifier: License :: OSI Approved :: BSD License
Classifier: Operating System :: OS Independent
Requires-Python: >=3.6
License-File: LICENSE
